discord/__init__.py
discord/__main__.py
discord/abc.py
discord/activity.py
discord/appinfo.py
discord/asset.py
discord/audit_logs.py
discord/backoff.py
discord/channel.py
discord/client.py
discord/colour.py
discord/components.py
discord/context_managers.py
discord/embeds.py
discord/emoji.py
discord/enums.py
discord/errors.py
discord/file.py
discord/flags.py
discord/gateway.py
discord/guild.py
discord/http.py
discord/integrations.py
discord/interactions.py
discord/invite.py
discord/iterators.py
discord/member.py
discord/mentions.py
discord/message.py
discord/mixins.py
discord/object.py
discord/oggparse.py
discord/opus.py
discord/partial_emoji.py
discord/permissions.py
discord/player.py
discord/py.typed
discord/raw_models.py
discord/reaction.py
discord/role.py
discord/shard.py
discord/stage_instance.py
discord/state.py
discord/sticker.py
discord/team.py
discord/template.py
discord/threads.py
discord/user.py
discord/utils.py
discord/voice_client.py
discord/widget.py
discord/bin/libopus-0.x64.dll
discord/bin/libopus-0.x86.dll
discord/ext/__init__.py
discord/ext/__pycache__/__init__.cpython-313.pyc
discord/ext/commands/__init__.py
discord/ext/commands/_types.py
discord/ext/commands/bot.py
discord/ext/commands/cog.py
discord/ext/commands/context.py
discord/ext/commands/converter.py
discord/ext/commands/cooldowns.py
discord/ext/commands/core.py
discord/ext/commands/errors.py
discord/ext/commands/flags.py
discord/ext/commands/help.py
discord/ext/commands/view.py
discord/ext/commands/__pycache__/__init__.cpython-312.pyc
discord/ext/commands/__pycache__/__init__.cpython-313.pyc
discord/ext/commands/__pycache__/_types.cpython-312.pyc
discord/ext/commands/__pycache__/_types.cpython-313.pyc
discord/ext/commands/__pycache__/bot.cpython-312.pyc
discord/ext/commands/__pycache__/bot.cpython-313.pyc
discord/ext/commands/__pycache__/cog.cpython-312.pyc
discord/ext/commands/__pycache__/cog.cpython-313.pyc
discord/ext/commands/__pycache__/context.cpython-312.pyc
shadowcord-1.7.5.dist-info/licenses/LICENSE
shadowcord-1.7.5.dist-info/METADATA
shadowcord-1.7.5.dist-info/WHEEL
shadowcord-1.7.5.dist-info/top_level.txt
shadowcord-1.7.5.dist-info/RECORD
